aligned_bert_embedder/AlignedBertEmbedder.py
aligned_bert_embedder/__init__.py
aligned_bert_embedder/__main__.py
aligned_bert_embedder/utils/__init__.py
aligned_bert_embedder/utils/alignment.py
aligned_bert_embedder/utils/etc.py
aligned_bert_embedder/utils/modeling.py
aligned_bert_embedder/utils/tokenization.py
aligned_bert_embedder-0.81.data/scripts/aligned_bert_embedder
aligned_bert_embedder-0.81.data/scripts/aligned_bert_embedder_
aligned_bert_embedder-0.81.dist-info/LICENSE
aligned_bert_embedder-0.81.dist-info/METADATA
aligned_bert_embedder-0.81.dist-info/WHEEL
aligned_bert_embedder-0.81.dist-info/top_level.txt
aligned_bert_embedder-0.81.dist-info/RECORD
