Metadata-Version: 2.1
Name: aligned-bert-embedder
Version: 0.81
Summary: Module for generating aligned contextualized bert embeddings using different strategies
Home-page: https://github.com/zeionara/aligned_bert_embedder
Author-email: zeionara@gmail.com
License: UNKNOWN
Platform: UNKNOWN
Classifier: Programming Language :: Python :: 3
Classifier: License :: OSI Approved :: Apache Software License
Classifier: Operating System :: OS Independent
